LICENSE
MANIFEST.in
README.md
pyproject.toml
setup.cfg
setup.py
binhash/__init__.py
binhash/fields.py
django_binhash.egg-info/PKG-INFO
django_binhash.egg-info/SOURCES.txt
django_binhash.egg-info/dependency_links.txt
django_binhash.egg-info/not-zip-safe
django_binhash.egg-info/requires.txt
django_binhash.egg-info/top_level.txt
tests/.DS_Store
tests/__init__.py
tests/models.py
tests/settings.py
tests/test_fields.py