Metadata-Version: 2.1
Name: django-binhash
Version: 0.2.0
Summary: Work with hexadecimal, store in binary, using half of the data size.
Home-page: https://github.com/racum/django-binhash
Author: Ronaldo Racum
Author-email: ronaldo@racum.com
License: BSD-3-Clause
Keywords: binhash
Classifier: Intended Audience :: Developers
Classifier: License :: OSI Approved :: BSD License
Classifier: Natural Language :: English
Classifier: Programming Language :: Python :: 3
Classifier: Programming Language :: Python :: 3 :: Only
Classifier: Programming Language :: Python :: 3.10
Classifier: Programming Language :: Python :: 3.11
Classifier: Programming Language :: Python :: 3.12
Requires-Python: >=3.10
License-File: LICENSE
Requires-Dist: django
